{
  "version": "1.0",
  "description": "汉献帝之末路 v3.1 科技树定义 (15节点 / 3主线)",
  "lines": {
    "农本": "发展农业, 充实国库",
    "王权": "巩固皇权, 强化法统",
    "军备": "强军备战, 威震四方"
  },
  "techs": [
    {"id": "agri_basic", "name": "初农", "line": "农本", "tier": 0, "cost": 0,
     "description": "开垦基本农田, 每年粮食产量 +10%",
     "effects": {"grain_output": 0.10, "population_growth": 0.02},
     "prerequisites": [], "unlocks": ["agri_water"]},
    {"id": "agri_water", "name": "水利", "line": "农本", "tier": 1, "cost": 30,
     "description": "兴修水利, 农田旱涝保收",
     "effects": {"grain_output": 0.20, "disaster_resist": 0.10},
     "prerequisites": ["agri_basic"], "unlocks": ["agri_tuntian"]},
    {"id": "agri_tuntian", "name": "屯田", "line": "农本", "tier": 2, "cost": 80,
     "description": "募民屯田, 充实边郡",
     "effects": {"grain_output": 0.30, "border_garrison": 5, "fiscal": 0.10},
     "prerequisites": ["agri_water"], "unlocks": ["agri_tools"]},
    {"id": "agri_tools", "name": "曲辕犁", "line": "农本", "tier": 3, "cost": 150,
     "description": "改进农具, 精耕细作",
     "effects": {"grain_output": 0.40, "population_growth": 0.05, "fiscal": 0.15},
     "prerequisites": ["agri_tuntian"], "unlocks": ["agri_reform"]},
    {"id": "agri_reform", "name": "土改新政", "line": "农本", "tier": 4, "cost": 300,
     "description": "授田于民, 国泰民安",
     "effects": {"grain_output": 0.50, "peasant_loyalty": 0.30, "fiscal": 0.25, "民心": 0.20},
     "prerequisites": ["agri_tools"], "unlocks": []},

    {"id": "law_basic", "name": "律法", "line": "王权", "tier": 0, "cost": 0,
     "description": "颁布汉律, 纲常有序",
     "effects": {"legal_clarity": 0.10, "imperial_authority": 0.05},
     "prerequisites": [], "unlocks": ["law_wen"]},
    {"id": "law_wen", "name": "文书", "line": "王权", "tier": 1, "cost": 30,
     "description": "设尚书台, 公文通达",
     "effects": {"admin_efficiency": 0.15, "fiscal": 0.05},
     "prerequisites": ["law_basic"], "unlocks": ["law_math"]},
    {"id": "law_math", "name": "算学", "line": "王权", "tier": 2, "cost": 80,
     "description": "兴算学, 户籍田亩皆可核",
     "effects": {"tax_collection": 0.20, "census_accuracy": 0.30, "fiscal": 0.10},
     "prerequisites": ["law_wen"], "unlocks": ["law_central"]},
    {"id": "law_central", "name": "中央集权", "line": "王权", "tier": 3, "cost": 150,
     "description": "推恩令, 削藩集权",
     "effects": {"vassal_loyalty": 0.25, "imperial_authority": 0.30, "fiscal": 0.20},
     "prerequisites": ["law_math"], "unlocks": ["law_legitimacy"]},
    {"id": "law_legitimacy", "name": "法统正统", "line": "王权", "tier": 4, "cost": 300,
     "description": "定鼎之功, 万世法统",
     "effects": {"imperial_authority": 0.50, "succession_stability": 0.40, "法统": 0.30, "威望": 0.20},
     "prerequisites": ["law_central"], "unlocks": []},

    {"id": "mil_basic", "name": "冶铁", "line": "军备", "tier": 0, "cost": 0,
     "description": "冶铁成兵, 装备初成",
     "effects": {"unit_attack": 0.10, "unit_defense": 0.05},
     "prerequisites": [], "unlocks": ["mil_tactic"]},
    {"id": "mil_tactic", "name": "兵法", "line": "军备", "tier": 1, "cost": 30,
     "description": "研习兵法, 阵法初成",
     "effects": {"unit_attack": 0.15, "unit_defense": 0.10, "morale": 0.10},
     "prerequisites": ["mil_basic"], "unlocks": ["mil_intel"]},
    {"id": "mil_intel", "name": "间谍", "line": "军备", "tier": 2, "cost": 80,
     "description": "遣间探敌, 知己知彼",
     "effects": {"intel_quality": 0.30, "sabotage_chance": 0.20, "unit_attack": 0.05},
     "prerequisites": ["mil_tactic"], "unlocks": ["mil_elite"]},
    {"id": "mil_elite", "name": "精兵", "line": "军备", "tier": 3, "cost": 150,
     "description": "百战精兵, 以一当十",
     "effects": {"unit_attack": 0.30, "unit_defense": 0.20, "morale": 0.30, "军力": 0.15},
     "prerequisites": ["mil_intel"], "unlocks": ["mil_legend"]},
    {"id": "mil_legend", "name": "百战雄狮", "line": "军备", "tier": 4, "cost": 300,
     "description": "百战之师, 威震天下",
     "effects": {"unit_attack": 0.50, "unit_defense": 0.40, "morale": 0.50, "intimidation": 0.30, "军力": 0.30, "威望": 0.20},
     "prerequisites": ["mil_elite"], "unlocks": []}
  ]
}
